pypianotune/__init__.py
pypianotune/pypianotune.py
PyPianoTune-0.1.5.dist-info/LICENSE
PyPianoTune-0.1.5.dist-info/METADATA
PyPianoTune-0.1.5.dist-info/WHEEL
PyPianoTune-0.1.5.dist-info/top_level.txt
PyPianoTune-0.1.5.dist-info/RECORD
