Metadata-Version: 2.1
Name: PyPianoTune
Version: 0.1.5
Summary: A Python module to convert music notes into piano tune.
Author-email: Kelvin Xu <xxk59@hotmail.com>
Project-URL: Homepage, https://github.com/xxk59/piano_tune
Project-URL: Issues, https://github.com/xxk59/piano_tune/issues
Classifier: Programming Language :: Python :: 3
Classifier: License :: OSI Approved :: MIT License
Classifier: Operating System :: OS Independent
Requires-Python: >=3.8
License-File: LICENSE
